[{"title":"திருப்பத்தூர் மாவட்ட தேமுதிக செயலாளர் அண்ணன் அடித்துக் கொலை: 4 பேர் கைது","text":"<a href=\"https:\/\/www.dinakaran.com\/www.Dinakaran.com\/latest_Detail.asp?Nid=682378\"><img align=\"left\" border=\"0\" src=\"http:\/\/img.dinakaran.com\/data1\/DNewsimages\/Tamil_News_6_9_2021_79084415.jpg\" style=\"margin: 10px 0 0 10px; padding: 4px;\" \/><\/a><p><figure>திருப்பத்தூர்: திருப்பத்தூர் மாவட்ட தேமுதிக செயலாளர் ஹரிகிருஷ்ணனின் அண்ணன் மாதேஸ்வரன் அடித்துக் கொலை செய்யப்பட்டார். இந்த சம்பவம் தொடர்பாக 4 பேர் கைது செய்யப்பட்டு சிறையில் அடைக்கப்பட்டனர். கந்திலி அருகே எர்ரம்பட்டியில் ஞானவேல் என்பவருக்கும் ஹரிகிருஷ்ணனுக்கும் இடையே ஏற்பட்ட தகராறில் கொலை செய்யப்பட்டார்.&nbsp;<\/figure><\/p>","link":"http:\/\/www.dinakaran.com\/Latest_Detail.asp?Nid=682378","image":["http:\/\/img.dinakaran.com\/data1\/DNewsimages\/Tamil_News_6_9_2021_79084415.jpg"],"pubdate":"9-6-2021 8:56"},{"title":"மேட்டூர் அணையின் நீர்மட்டம் 96.78 அடியாக குறைவு, விநாடிக்கு 750 கனஅடி நீர் திறப்பு","text":"<a href=\"https:\/\/www.dinakaran.com\/www.Dinakaran.com\/latest_Detail.asp?Nid=682377\"><img align=\"left\" border=\"0\" src=\"http:\/\/img.dinakaran.com\/data1\/DNewsimages\/Tamil_News_6_9_2021_28278751.jpg\" style=\"margin: 10px 0 0 10px; padding: 4px;\" \/><\/a><p><figure>சேலம்: மேட்டூர் அணையின் நீர்மட்டம் 96.78 அடியாக குறைந்துள்ளது. மேலும் நீர் இருப்பு 60.74 டிஎம்சியாகவும் உள்ளது. அணைக்கு நீர்வரத்து 1,181 கனஅடியாகவும் அதிகரித்துள்ளது. மேலும் குடிநீர் தேவைக்காக விநாடிக்கு 750 கனஅடி நீர் திறக்கப்பட்டுள்ளது.<\/figure><\/p>","link":"http:\/\/www.dinakaran.com\/Latest_Detail.asp?Nid=682377","image":["http:\/\/img.dinakaran.com\/data1\/DNewsimages\/Tamil_News_6_9_2021_28278751.jpg"],"pubdate":"9-6-2021 8:50"},{"title":"தமிழகத்தில் ஒரு சிமெண்ட் மூட்டை விலை ரூ.370லிருந்து ரூ.520-ஆக உயர்வு: கட்டுமான பொறியாளர்கள்","text":"<a href=\"https:\/\/www.dinakaran.com\/www.Dinakaran.com\/latest_Detail.asp?Nid=682375\"><img align=\"left\" border=\"0\" src=\"http:\/\/img.dinakaran.com\/data1\/DNewsimages\/Tamil_News_6_9_2021_46195621.jpg\" style=\"margin: 10px 0 0 10px; padding: 4px;\" \/><\/a><p><figure>சென்னை:&nbsp; தமிழகத்தில் ஒரு சிமெண்ட் மூட்டை விலை ரூ.370லிருந்து ரூ.520-ஆக உயர்ந்துள்ளது என கட்டுமான பொறியாளர்கள் கூறுகின்றனர். ஊரடங்கு காரணமாக கட்டுமான பொருட்களின் விலை உயர்ந்துள்ளது என அனைத்து கட்டுமான பொறியாளர்கள் சங்கம் கூறியுள்ளது.&nbsp;<\/figure><\/p>","link":"http:\/\/www.dinakaran.com\/Latest_Detail.asp?Nid=682375","image":["http:\/\/img.dinakaran.com\/data1\/DNewsimages\/Tamil_News_6_9_2021_46195621.jpg"],"pubdate":"9-6-2021 8:38"},{"title":"தமிழக முதல்வரிடம் பொதுமக்கள் புகார் அளிக்க வசதியாக முதல்வரின் தனிப்பிரிவு இணையத்தளம் புதிதாக தொடக்கம்","text":"<a href=\"https:\/\/www.dinakaran.com\/www.Dinakaran.com\/latest_Detail.asp?Nid=682374\"><img align=\"left\" border=\"0\" src=\"http:\/\/img.dinakaran.com\/data1\/DNewsimages\/Tamil_News_6_9_2021_39551944.jpg\" style=\"margin: 10px 0 0 10px; padding: 4px;\" \/><\/a><p><figure>சென்னை: தமிழக முதல்வரிடம் பொதுமக்கள் புகார் அளிக்க வசதியாக முதல்வரின் தனிப்பிரிவு இணையத்தளம் புதிதாக தொடங்கப்பட்டுள்ளது. www.cmcell.tn.gov.in\/register.php என்ற இணையதளத்தில் புகார் அளிக்கலாம் என கூறப்பட்டுள்ளது. பொதுமக்கள் அளிக்கும் புகார் குறித்து எடுக்கப்பட்ட நடவடிக்கை பற்றியும் இணையதளத்தில் அறிந்து கொள்ளலாம் என கூறப்பட்டுள்ளது.&nbsp;<\/figure><\/p>","link":"http:\/\/www.dinakaran.com\/Latest_Detail.asp?Nid=682374","image":["http:\/\/img.dinakaran.com\/data1\/DNewsimages\/Tamil_News_6_9_2021_39551944.jpg"],"pubdate":"9-6-2021 8:23"},{"title":"கொரோனா நிவாணத் தொகையை தாமதிக்காமல் அந்தந்த துறை தலைவர்கள் உடனடியாக வழங்க அரசு உத்தரவு","text":"<a href=\"https:\/\/www.dinakaran.com\/www.Dinakaran.com\/latest_Detail.asp?Nid=682373\"><img align=\"left\" border=\"0\" src=\"http:\/\/img.dinakaran.com\/data1\/DNewsimages\/Tamil_News_6_9_2021_2932376.jpg\" style=\"margin: 10px 0 0 10px; padding: 4px;\" \/><\/a><p><figure>சென்னை: கொரோனா நிவாணத் தொகையை தாமதிக்காமல் அந்தந்த துறை தலைவர்கள் உடனடியாக வழங்க அரசு உத்தரவிட்டுள்ளது. முன்களப்பணியாளர்களுக்கான அரசின் நிவாரண தொகையை சம்பந்தப்பட்டவர்களுக்கு உடனே வழங்குக என தமிழக அரசு கூறியுள்ளது.&nbsp;<\/figure><\/p>","link":"http:\/\/www.dinakaran.com\/Latest_Detail.asp?Nid=682373","image":["http:\/\/img.dinakaran.com\/data1\/DNewsimages\/Tamil_News_6_9_2021_2932376.jpg"],"pubdate":"9-6-2021 8:18"},{"title":"கொரோனா தடுப்பூசி போட பதிவு செய்யும் கோவின் இணையதளத்தில் தமிழ் மொழி சேர்ப்பு","text":"<a href=\"https:\/\/www.dinakaran.com\/www.Dinakaran.com\/latest_Detail.asp?Nid=682372\"><img align=\"left\" border=\"0\" src=\"http:\/\/img.dinakaran.com\/data1\/DNewsimages\/Tamil_News_6_9_2021_39832706.jpg\" style=\"margin: 10px 0 0 10px; padding: 4px;\" \/><\/a><p><figure>டெல்லி: கொரோனா தடுப்பூசி போட பதிவு செய்யும் கோவின் இணையதளத்தில்&nbsp;தமிழ் மொழி சேர்க்கப்பட்டுள்ளது. இந்தி, மராட்டி, குஜராத்தி உள்ளிட்ட மாநில மொழிகள் சேர்க்கப்பட்ட நிலையில் தமிழ் சேர்க்கப்படாமல் இருந்தது. மாநில மொழிகள் சேர்க்கப்பட்ட நிலையில் தமிழ் மொாழி சேதர்க்கப்படாததற்கு கடும் கண்டனம் எழுந்தது.<\/figure><\/p>","link":"http:\/\/www.dinakaran.com\/Latest_Detail.asp?Nid=682372","image":["http:\/\/img.dinakaran.com\/data1\/DNewsimages\/Tamil_News_6_9_2021_39832706.jpg"],"pubdate":"9-6-2021 7:58"},{"title":"வண்டலூர் உயிரியல் பூங்காவில் உள்ள விலங்குகளை தத்தெடுக்க பூங்கா நிர்வாகம் வேண்டுக்கோள்","text":"<a href=\"https:\/\/www.dinakaran.com\/www.Dinakaran.com\/latest_Detail.asp?Nid=682371\"><img align=\"left\" border=\"0\" src=\"http:\/\/img.dinakaran.com\/data1\/DNewsimages\/Tamil_News_6_9_2021_56803531.jpg\" style=\"margin: 10px 0 0 10px; padding: 4px;\" \/><\/a><p><figure>சென்னை: வண்டலூர் உயிரியல் பூங்காவில் உள்ள விலங்குகளை தத்தெடுக்க பூங்கா நிர்வாகம் வேண்டுக்கோள் விடுத்துள்ளது. விலங்குகளை தத்தெடுக்கும் திட்டத்தில்&nbsp; குறைந்தது ரூ.100 செலுத்தி விலங்குகளை தத்தெடுக்க வாருங்கள் என கூறியுள்ளது. பூங்காவில் சிங்கம், புலி, சிறுத்தை, யானை, பறவைகள் உள்பட 2,382 விலங்குகள் பராமரிக்கப்பட்டு வருகின்றன.&nbsp;<\/figure><\/p>","link":"http:\/\/www.dinakaran.com\/Latest_Detail.asp?Nid=682371","image":["http:\/\/img.dinakaran.com\/data1\/DNewsimages\/Tamil_News_6_9_2021_56803531.jpg"],"pubdate":"9-6-2021 7:49"},{"title":"ஜூன்-09: தொடர்ந்து உயரும் பெட்ரோல், டீசல் விலை.,! பெட்ரோல் விலை ரூ.96.94, டீசல் விலை ரூ.91.15","text":"<p>சென்னை: பெட்ரோல் மற்றும் டீசல் விலை தினமும் மாற்றி அமைக்கப்படுகிறது. ஆனால் இன்று நேற்றைய விலையில் மாற்றமில்லை. அதன் அடிப்படையில் இன்றைய பெட்ரோல் விலை லிட்டருக்கு ரூ.96.94,ஆகவும், டீசல் விலை லிட்டருக்கு ரூ.91.15-ஆகவும் நிர்ணயம் செய்யப்பட்டுள்ளது. இந்த விலை இன்று காலை 6 மணி முதல் அமலுக்கு வந்தது. <\/p>","link":"http:\/\/www.dinakaran.com\/Latest_Detail.asp?Nid=682366","image":["https:\/\/img.dinakaran.com\/data1\/DNewsimages\/"],"pubdate":"9-6-2021 6:52"},{"title":"சென்னையில் ஆபரணத் தங்கத்தின் விலை சவரனுக்கு ரூ.80 உயர்ந்து, ரூ.37,040 -க்கு விற்பனை","text":"<a href=\"https:\/\/www.dinakaran.com\/www.Dinakaran.com\/latest_Detail.asp?Nid=682383\"><img align=\"left\" border=\"0\" src=\"http:\/\/img.dinakaran.com\/data1\/DNewsimages\/Tamil_News_6_9_2021_24518985.jpg\" style=\"margin: 10px 0 0 10px; padding: 4px;\" \/><\/a><p>சென்னை: சென்னையில் ஆபரணத் தங்கத்தின் விலை சவரனுக்கு ரூ.80 உயர்ந்து, ரூ.37,040 -க்கு விற்பனை செய்யப்படுகிறது. ஆபரணத் தங்கத்தின் விலை ஒரு கிராம் 10 உயர்ந்து ரூ.4,630-க்கு விற்பனை ஆகிறது. மேலும் சென்னையில் சில்லறை வர்த்தகத்தில் ஒரு கிராம் வெள்ளியின் விலை ரூ.76.10-க்கு விற்பனை செய்யப்படுகிறது.<\/p>","link":"http:\/\/www.dinakaran.com\/Latest_Detail.asp?Nid=682383","image":["http:\/\/img.dinakaran.com\/data1\/DNewsimages\/Tamil_News_6_9_2021_24518985.jpg"],"pubdate":"9-6-2021 10:3"},{"title":"பழனியில் மொத்த வியாபார மளிகை கடைகளை திறக்க அனுமதி கோரி வியாபாரிகள் போராட்டம்","text":"<a href=\"https:\/\/www.dinakaran.com\/www.Dinakaran.com\/latest_Detail.asp?Nid=682388\"><img align=\"left\" border=\"0\" src=\"http:\/\/img.dinakaran.com\/data1\/DNewsimages\/Tamil_News_6_9_2021_53411502.jpg\" style=\"margin: 10px 0 0 10px; padding: 4px;\" \/><\/a><p>பழனி: பழனியில் மொத்த வியாபார மளிகை கடைகளை திறக்க அனுமதி கோரி வியாபாரிகள் போராட்டத்தில் ஈடுபட்டுள்ளனர். பழனி காந்தி மார்க்கெட்டில் 60-க்கும் மேற்பட்ட மொத்த வியாபார மளிகை கடைகள் செயல்பட்டு வருகின்றன.<\/p>","link":"http:\/\/www.dinakaran.com\/Latest_Detail.asp?Nid=682388","image":["http:\/\/img.dinakaran.com\/data1\/DNewsimages\/Tamil_News_6_9_2021_53411502.jpg"],"pubdate":"9-6-2021 10:21"},{"title":"கொரோனா தடுப்பு பணிகள் குறித்து இன்று மாலை ஆளுநர் பன்வாரிலால் புரோகித்தை சந்திக்கிறார் முதல்வர் மு.க.ஸ்டாலின் !","text":"<a href=\"https:\/\/www.dinakaran.com\/www.Dinakaran.com\/latest_Detail.asp?Nid=682382\"><img align=\"left\" border=\"0\" src=\"http:\/\/img.dinakaran.com\/data1\/DNewsimages\/Tamil_News_6_9_2021_61227054.jpg\" style=\"margin: 10px 0 0 10px; padding: 4px;\" \/><\/a><p>சென்னை: கொரோனா தடுப்பு பணிகள் குறித்து விளக்கம் அளிக்க இன்று மாலை ஆளுநர் பன்வாரிலால் புரோகித்தை முதல்வர் மு.க.ஸ்டாலின் சந்திக்க உள்ளார். மேலும், சட்டப்பேரவை கூட்டத்தில் உரையாற்ற ஆளுநருக்கு முறைப்படி அழைப்பு விடுக்கப்பட உள்ளதாக தகவல் வெளியாகி உள்ளது. <\/p>","link":"http:\/\/www.dinakaran.com\/Latest_Detail.asp?Nid=682382","image":["http:\/\/img.dinakaran.com\/data1\/DNewsimages\/Tamil_News_6_9_2021_61227054.jpg"],"pubdate":"9-6-2021 10:2"},{"title":"தமிழ்நாட்டில் 34 மாவட்டங்களில் கொரோனா தடுப்பூசி இருப்பு இல்லை: ப.சிதம்பரம் தகவல்","text":"<a href=\"https:\/\/www.dinakaran.com\/www.Dinakaran.com\/latest_Detail.asp?Nid=682386\"><img align=\"left\" border=\"0\" src=\"http:\/\/img.dinakaran.com\/data1\/DNewsimages\/Tamil_News_6_9_2021_38439578.jpg\" style=\"margin: 10px 0 0 10px; padding: 4px;\" \/><\/a><p>சென்னை: தமிழ்நாட்டில் 34 மாவட்டங்களில் கொரோனா தடுப்பூசி இருப்பு இல்லை என்று முன்னாள் அமைச்சர் ப.சிதம்பரம் தெரிவித்துள்ளார். தடுப்பூசி போடுவது ஜூன் 2ம் தேதியில் இருந்து ஏறத்தாழ மாநிலம் முழுவதும் நிறுத்தப்பட்டுள்ளது. இது, ஒன்றிய அரசின் தடுப்பூசி தயாரிப்பு மற்றும் கொள்முதல் கொள்கைகள்தான் இந்நிலைக்கு முழு முதற்காரணம் என்று தெரிவித்துள்ளார்.<\/p>","link":"http:\/\/www.dinakaran.com\/Latest_Detail.asp?Nid=682386","image":["http:\/\/img.dinakaran.com\/data1\/DNewsimages\/Tamil_News_6_9_2021_38439578.jpg"],"pubdate":"9-6-2021 10:16"},{"title":"ராணிப்பேட்டை மாவட்டம் ரத்தினகிரி அருகே டாஸ்மாக் கடையில் 1.5 லட்சம் மதிப்பிலான மது பாட்டில்கள் திருட்டு","text":"<a href=\"https:\/\/www.dinakaran.com\/www.Dinakaran.com\/latest_Detail.asp?Nid=682385\"><img align=\"left\" border=\"0\" src=\"http:\/\/img.dinakaran.com\/data1\/DNewsimages\/Tamil_News_6_9_2021_87566776.jpg\" style=\"margin: 10px 0 0 10px; padding: 4px;\" \/><\/a><p>ராணிப்பேட்டை: ராணிப்பேட்டை மாவட்டம் ரத்தினகிரி அருகே டாஸ்மாக் கடையில் 1.5 லட்சம் மதிப்பிலான மது பாட்டில்கள் கொள்ளையடிக்கப்பட்டுள்ளது. நந்தியாலம் பகுதியில் அமைந்துள்ள டாஸ்மாக் கடையின் சுவற்றில் துளையிட்டு மது பாட்டில்களை கொள்ளையடித்தது தொடர்பாக போலீசார் விசாரணையில் ஈடுபட்டுள்ளனர்.<\/p>","link":"http:\/\/www.dinakaran.com\/Latest_Detail.asp?Nid=682385","image":["http:\/\/img.dinakaran.com\/data1\/DNewsimages\/Tamil_News_6_9_2021_87566776.jpg"],"pubdate":"9-6-2021 10:10"},{"title":"அரியலூர்: தூங்கிக்கொண்டிருந்த கணவன், மனைவி கொலை; நகையை திருடிச் சென்ற மர்மகும்பல்","text":"<p><img src=\"https:\/\/ptm-cms-images.sgp1.cdn.digitaloceanspaces.com\/uploads\/news-image\/2021\/06\/09\/800x400\/121001.webp\" \/><\/p><p><strong>அரியலூர் மாவட்டத்தில் தூங்கிக் கொண்டிருந்த கணவன் மனைவியை அடித்துக் கொலை செய்து தப்பிச்சென்ற மர்மநபர்களை காவல்துறையினர் தேடி வருகின்றனர்.&nbsp;<\/strong><br \/> <br \/>அரியலூர் அருகே உள்ள அல்லிநகரம் கிராமத்தை சேர்ந்த தம்பதி பெரியசாமி (62). தனது முதல் மனைவியை இழந்த பெரியசாமி இரண்டாவதாக அறிவழகியை (48) திருமணம் செய்து கொண்டுள்ளார். இவர்களுக்கு முருகானந்தம் என்ற மகனும் மற்றும் சத்யா என்ற மகளும் உள்ளனர். முருகானந்தம் சென்னையில் உள்ள தனியார் நிறுவனமொன்றில் பணியாற்றி வருகிறார். சத்யாவிற்கு திருமணம் முடிந்து கணவர் வெங்கடேசனுடன் வசித்து வந்தார்.<\/p>\n<p><img alt=\"image\" src=\"https:\/\/ptm-cms-images.sgp1.cdn.digitaloceanspaces.com\/uploads\/news-image\/moreimages\/1623211127247.jpeg\" width=\"700\" \/><\/p>\n<p>இந்தநிலையில் இன்று காலை முதலே பெரியசாமியும் அவரது மனைவியும் வீட்டை விட்டு வெளியே வரவில்லை எனத் தெரிகிறது. இந்ததகவலை அக்கம்பக்கத்தினர் உறவினர்களிடம் கூற, அவர்கள் வீட்டிற்கு வந்து பார்த்துள்ளனர். வீட்டின் வெளிப்புறக்கதவு பூட்டியிருந்த நிலையில், சந்தேகமடைந்து வீட்டின் உள்ளே சென்று பார்த்துள்ளனர். அப்போது பெரியசாமியும் அவரது மனைவியும் ரத்த வெள்ளத்தில் பிணமாக கிடந்தனர். மேலும் அறிவழகியின் கழுத்து, கைகளில் கிடந்த நகைகளையும் கொள்ளையர்கள் திருடிச்சென்றுள்ளனர்.<\/p>\n<p>இதனைத்தொடர்ந்து போலீசார் நடத்திய விசாரணையில், அதிகாலை வேளையில் 3 நபர்கள் டவுசர் மட்டும் அணிந்து கொண்டு இருசக்கர வாகனத்தில் சென்றது தெரியவந்தது. மேற்கொண்டு போலீசார் விசாரணையை தீவிரப்படுத்தியுள்ளனர்.<\/p><p><a href=\"http:\/\/puthiyathalaimurai.com\/newsview\/105691\/the-mysterious-gang-who-beat-and-stole-the-Jewellery.html\" style=\"color: #FF4422;\" target=\"_blank\">Source : WWW.PUTHIYATHALAIMURAI.COM<\/a><\/p>","link":"http:\/\/puthiyathalaimurai.com\/newsview\/105691\/the-mysterious-gang-who-beat-and-stole-the-Jewellery.html","image":["https:\/\/ptm-cms-images.sgp1.cdn.digitaloceanspaces.com\/uploads\/news-image\/2021\/06\/09\/800x400\/121001.webp","https:\/\/ptm-cms-images.sgp1.cdn.digitaloceanspaces.com\/uploads\/news-image\/moreimages\/1623211127247.jpeg"],"pubdate":"2021-06-09T09:58:02+00:00"},{"title":"கடல்போல் காட்சியளிக்கும் வைகை அணை: பருந்துப் பார்வை காட்சி","text":"<p><img src=\"https:\/\/ptm-cms-images.sgp1.cdn.digitaloceanspaces.com\/uploads\/news-image\/2021\/06\/09\/800x400\/120997.webp\" \/><\/p><p>தென்மேற்கு பருவமழை தொடங்கியுள்ள சில தினங்களிலேயே முழு கொள்ளளவை எட்டும் நிலையில் உள்ளது வைகை அணை. அதன் எழில்மிகு காட்சியை பருந்துப்பார்வையில் பதிவு செய்துள்ளது புதிய தலைமுறை.<\/p>\n<p>தேனி மாவட்டம் ஆண்டிபட்டி அருகே அமைந்துள்ள வைகை அணையின் மொத்த பரப்பளவு 15 சதுர கிலோ மீட்டர். 71 அடி உயரம் கொண்ட வைகை அணையின் மூலம் தேனி, திண்டுக்கல், மதுரை, ராமநாதபுரம், சிவகங்கை மாவட்டங்கள் பாசன வசதி பெறுகின்றன. இந்த ஐந்து மாவட்ட மக்களின் குடிநீர் ஆதாரமும் வைகை அணை தான். சுருளி மலை, குமுளி மலை, மேகமலை, வெள்ளி மலை, சதுரகிரிமலை, வருசநாடு மலை, குரங்கணி உள்ளிட்ட மேற்குத்தொடர்ச்சி மலைப்பகுதிகள் வைகை அணையின் முக்கிய நீர்ப்பிடிப்பு பகுதிகளாகும். நீர்ப்பிடிப்பு பகுதிகளில் பெய்யும் மழை நீர் மூல வைகையாறு, கொட்டக்குடி ஆறுகள் மூலமும், முல்லைப்பெரியாறு அணையில் இருந்து திறக்கப்படும் தண்ணீர் லோயர்கேம்ப்பில் இருந்து முல்லைப்பெரியாற்றின் மூலமும் வைகை அணையை வந்தடைகிறது.<\/p>\n<p>கடந்த ஜனவரியில் எதிர்பாராமல் கிடைத்த வடகிழக்கு பருவமழை, கடந்த மாதம் கிடைத்த கோடை மழை, சில தினங்களுக்கு முன்பு பெய்யத் தொடங்கிய தென்கிழக்கு பருவமழை ஆகியவற்றால் அணையின் நீர்மட்டம் உயர்ந்து வருகிறது. 71 அடி உயரம் கொண்ட வைகை அணையின் நீர்மட்டம் 67.70 அடியாக உள்ளது. முழு கொள்ளவை எட்ட இன்னும் சில அடிகளே உள்ள நிலையில் அணை முழுவதும் தண்ணீர் நிரம்பி கடல் போல் காணப்படுகிறது. பருந்துப்பார்வையில் பார்க்கும் போது பேரழகுடன் காட்சி அளிக்கிறது வைகை அணை. வைகை அணையின் பருந்துப்பார்வை காட்சியை வீடியோவில் காணலாம்.<\/p><p><a href=\"http:\/\/puthiyathalaimurai.com\/newsview\/105687\/Southwest-Monsoon-begins--Vaigai-Dam-reaches-full-capacity.html\" style=\"color: #FF4422;\" target=\"_blank\">Source : WWW.PUTHIYATHALAIMURAI.COM<\/a><\/p>","link":"http:\/\/puthiyathalaimurai.com\/newsview\/105687\/Southwest-Monsoon-begins--Vaigai-Dam-reaches-full-capacity.html","image":["https:\/\/ptm-cms-images.sgp1.cdn.digitaloceanspaces.com\/uploads\/news-image\/2021\/06\/09\/800x400\/120997.webp"],"pubdate":"2021-06-09T08:56:25+00:00"},{"title":"உ.பி: சரக்கு வாகனம் மீது அரசுப் பேருந்து மோதிய விபத்தில் 17 பேர் உயிரிழப்பு","text":"<p><img src=\"https:\/\/ptm-cms-images.sgp1.cdn.digitaloceanspaces.com\/uploads\/news-image\/2021\/06\/09\/800x400\/120994.webp\" \/><\/p><p>உத்தரப்பிரதேசத்தில் சிறிய ரக சரக்கு வாகனத்தில் அரசுப் பேருந்து மோதிய விபத்தில் 17 பேர் உயிரிழந்தனர்.<\/p>\n<p>கான்பூர் அருகே சச்சேந்தி என்ற இடத்தில் மூன்று சக்கர சிறிய ரக சரக்கு வாகனத்தில், அகமதாபாத் நோக்கி சென்று கொண்டிருந்த அரசு சொகுசுப் பேருந்து மோதி விபத்துக்குள்ளானது. இதில் சரக்கு வாகனம் தூக்கி வீசப்பட்ட நிலையில், பேருந்து நெடுஞ்சாலையில் உருண்டது. விபத்தில் பேருந்து பயணிகள் உள்ளிட்ட 17 பேர் நிகழ்விடத்திலேயே உயிரிழந்தனர். மேலும் பலர் படுகாயமுற்றனர். மீட்கப்பட்டவர்கள் மருத்துவமனைகளில் சேர்க்கப்பட்டனர்.<\/p>\n<p>விபத்து குறித்து அதிர்ச்சி தெரிவித்துள்ள பிரதமர் நரேந்திர மோடி, விபத்தில் உயிரிழந்தவர்களின் குடும்பத்தினருக்கு 2 லட்சம் ரூபாய் நிவாரணம் வழங்கப்படும் என்று அறிவித்துள்ளார். காயமுற்றோருக்கு 50 ஆயிரம் ரூபாய் வழங்கப்படுமென்றும் பிரதமர் அறிவித்துள்ளார்.<\/p><p><a href=\"http:\/\/puthiyathalaimurai.com\/newsview\/105684\/16-dead-around-30-injured-as-bus-collides-with-three-wheeler-in-UPs-Kanpur.html\" style=\"color: #FF4422;\" target=\"_blank\">Source : WWW.PUTHIYATHALAIMURAI.COM<\/a><\/p>","link":"http:\/\/puthiyathalaimurai.com\/newsview\/105684\/16-dead-around-30-injured-as-bus-collides-with-three-wheeler-in-UPs-Kanpur.html","image":["https:\/\/ptm-cms-images.sgp1.cdn.digitaloceanspaces.com\/uploads\/news-image\/2021\/06\/09\/800x400\/120994.webp"],"pubdate":"2021-06-09T07:34:39+00:00"},{"title":"சென்னை அண்ணாசாலையில் செயல்படும் பன்னோக்கு உயர் சிறப்பு மருத்துவமனை இடமாற்றம்?","text":"<p><img src=\"https:\/\/static.hindutamil.in\/hindu\/uploads\/news\/2021\/06\/09\/large\/680151.jpg\" \/><\/p><p>சென்னை அண்ணாசாலையில் செயல்படும் அரசு பன்னோக்கு உயர் சிறப்பு மருத்துவமனை கிண்டிக்கு மாற்றப்பட உள்ளதாக தகவல் வெளியாகியுள்ளது.<\/p>\n\n<p>சென்னை செயின்ட் ஜார்ஜ் கோட்டையில் செயல்படும் தலைமைச் செயலகத்தில் இடப் பற்றாக்குறை நிலவியதால், கடந்த திமுக ஆட்சியின்போது சென்னை அண்ணாசாலை ஓமந்தூரார் அரசினர் தோட்டத்தில் புதிய தலைமைச் செயலகம்கட்டப்பட்டது. சட்டப்பேரவை கூட்டத்தொடரும் புதிய தலைமைச் செயலகத்தில் நடைபெற்றது.<\/p>","link":"https:\/\/www.hindutamil.in\/news\/tamilnadu\/680151-chennai-multi-speciality-hospital.html?frm=rss_more_article","image":["https:\/\/static.hindutamil.in\/hindu\/uploads\/news\/2021\/06\/09\/large\/680151.jpg"],"pubdate":"2021-06-09T03:31:26+00:00"},{"title":"ஊரடங்கு கட்டுப்பாடுகள் தளர்வு: வாகன சோதனை தீவிரத்தை குறைத்துக்கொண்ட போலீஸார்","text":"<p><img src=\"https:\/\/static.hindutamil.in\/hindu\/uploads\/news\/2021\/06\/09\/large\/680152.jpg\" \/><\/p><p>ஊரடங்கு கட்டுப்பாடுகளில் தளர்வுகள் அளிக்கப்பட்டுள்ளதால், வாகன சோதனைகள் செய்வதை போலீஸார் குறைத்துள்ளனர்.<\/p>\n\n<p>கரோனா பரவல் தடுப்பு நடவடிக்கையாக தமிழகம் முழுவதும் வரும் 14-ம் தேதி வரை முழு ஊரடங்கு கடைபிடிக்கப்படுகிறது. இதில் பல்வேறு தளர்வுகள் அறிவிக்கப்பட்டுள்ளதால் போலீஸாரும் வாகன சோதனைகளின் தீவிரத்தைக் குறைத்துள் ளனர்.<\/p>","link":"https:\/\/www.hindutamil.in\/news\/tamilnadu\/680152-lockdown-relaxation.html?frm=rss_more_article","image":["https:\/\/static.hindutamil.in\/hindu\/uploads\/news\/2021\/06\/09\/large\/680152.jpg"],"pubdate":"2021-06-09T03:31:26+00:00"},{"title":"தமிழகத்தில் ஒப்பந்த அடிப்படையில் 1,485 மருத்துவர்களுக்கு பணி: சுகாதாரத் துறை அமைச்சர் தகவல்","text":"<p><img src=\"https:\/\/static.hindutamil.in\/hindu\/uploads\/news\/2021\/06\/09\/large\/680150.jpg\" \/><\/p><p>தமிழகத்தில் 1,485 மருத்துவர்கள் ஒப்பந்த அடிப்படையில் பணியில்சேர்க்கப்பட்டுள்ளதாக சுகாதாரத்துறை அமைச்சர் மா.சுப்பிரமணியன் தெரிவித்துள்ளார்.<\/p>\n\n<p>சென்னையில் உள்ள ஓமந்தூரார் அரசு மருத்துவ கல்லூரி மருத்துவமனையில் கரோனா நோயாளிகளின் உடல்நிலையை உறவினர்கள் அறிந்து கொள்வதற்காக டிஜிட்டல் தகவல் மற்றும் உதவி மையத்தை சுகாதாரத் துறை அமைச்சர் மா.சுப்பிரமணியன் தொடங்கி வைத்தார். தொடர்ந்து அடையாறு ஆனந்தபவன் சார்பில்வழங்கப்பட்ட ஆக்சிஜன் வசதியுடன் கூடிய 80 படுக்கைகளை பயன்பாட்டுக்கு கொண்டு வந்தார். இதையடுத்து, 70 மருத்துவர்களுக்கு தற்காலிக பணி நியமன ஆணைகளை வழங்கினார். பின்னர், செய்தியாளர்களிடம் அவர் கூறியதாவது:<\/p>","link":"https:\/\/www.hindutamil.in\/news\/tamilnadu\/680150-ma-subramaniyan.html?frm=rss_more_article","image":["https:\/\/static.hindutamil.in\/hindu\/uploads\/news\/2021\/06\/09\/large\/680150.jpg"],"pubdate":"2021-06-09T03:31:24+00:00"},{"title":"மத்திய அரசு சார்பில் நபர் ஒருவருக்கு ஒதுக்கீடு செய்த 5 கிலோ கூடுதல் அரிசி மொத்தமாக வழங்க முடிவு :","text":"<p><img src=\"https:\/\/static.hindutamil.in\/hindu\/uploads\/news\/2021\/06\/09\/large\/680140.jpg\" \/><\/p><p>அரிசி குடும்ப அட்டைதாரர்களுக்கு வழக்கமான அளவைவிட கூடு தலாக நபர் ஒருவருக்கு 5 கிலோ அரிசி இந்த மாதத்தில் மொத்தமாக வழங்கப்படும் என்று உணவுத்துறை தெரிவித்துள்ளது.<\/p>\n\n<p>இதுகுறித்து உணவுத்துறை வெளியிட்ட செய்திக்குறிப்பு: தமிழகத்தில் 2.09 கோடி அரிசி குடும்ப அட்டைதாரர்கள் உள்ளனர். அதில் 18.64 லட்சம் அந்தியோதயா அன்னயோஜனா பிரிவுக்கு மாதம் தோறும் அதிகபட்சம் 35 கிலோ வும் 93 லட்சம் முன்னுரிமை அட்டைதாரர்களுக்கு நபர் ஒருவருக்கு தலா 5 கிலோவும் மீதமுள்ள முன்னுரிமையற்ற குடும்ப அட்டைதாரர்களுக்கு 20 கிலோ இலவச அரிசியும் வழங் கப்படுகின்றன. அரிசி குடும்ப அட்டைதாரர்களின் தேவைக் கேற்ப புழுங்கல் அரிசி, பச்சரிசி என வாங்கிக் கொள்ளலாம்.<\/p>","link":"https:\/\/www.hindutamil.in\/news\/tamilnadu\/680140-5-kilo-rice.html?frm=rss_more_article","image":["https:\/\/static.hindutamil.in\/hindu\/uploads\/news\/2021\/06\/09\/large\/680140.jpg"],"pubdate":"2021-06-09T03:31:19+00:00"},{"title":"மாணவிகளுக்கு பாலியல் தொந்தரவு சென்னையில் மேலும் ஒரு தனியார் பள்ளி ஆசிரியர் கைது","text":"<p><img src=\"https:\/\/static.hindutamil.in\/hindu\/uploads\/news\/2021\/06\/09\/large\/680123.jpg\" \/><\/p><p>மாணவிகளுக்கு பாலியல் தொந்தரவு கொடுத்ததாக சென்னையில்மேலும் ஒரு தனியார் பள்ளி ஆசிரியர் கைது செய்யப்பட்டுள்ளார்.<\/p>\n\n<p>சென்னை அயனாவரத்தில் மகரிஷி வித்யா மந்திர் பள்ளி இயங்கி வருகிறது. இந்த பள்ளியில் திருவொற்றியூரை சேர்ந்த ஆனந்தன் (51) என்பவர் , 11, 12-ம்வகுப்புகளுக்கு வணிகவியல் பாடம் நடத்தி வந்தார். கடந்த 2014 முதல் 2016 வரை ஆனந்தனிடம் படித்த மாணவிகள் சிலர், பள்ளியில் படிக்கும்போது தங்களுக்கு ஆசிரியர் ஆனந்தன் பாலியல் தொல்லை கொடுத்ததாக சமூக ஊடகங்களில் தொடர்ந்து பதிவிட்டு வந்தனர்.<\/p>","link":"https:\/\/www.hindutamil.in\/news\/tamilnadu\/680123-private-school-teacher-arrested.html?frm=rss_more_article","image":["https:\/\/static.hindutamil.in\/hindu\/uploads\/news\/2021\/06\/09\/large\/680123.jpg"],"pubdate":"2021-06-09T03:31:13+00:00"},{"title":"விவசாயத்துக்காக வழங்கப்பட்ட நகைக் கடனுக்கான வட்டியில் 3% மானியம் வழங்க உத்தரவு: வங்கிகளுக்கு நபார்டு வங்கி சுற்றறிக்கை","text":"<p><img src=\"https:\/\/static.hindutamil.in\/hindu\/uploads\/news\/2021\/06\/09\/large\/680124.jpg\" \/><\/p><p>விவசாயத்துக்காக வழங்கப்பட்ட தங்க நகைக் கடனுக்கான வட்டியில், 3 சதவீதத்தை மானியமாக வழங்க அனைத்து வங்கிகளுக்கும் நபார்டு வங்கி சுற்றறிக்கை அனுப்பி உள்ளது.<\/p>\n\n<p>இதுகுறித்து வங்கி அதிகாரிகள் கூறியதாவது:<\/p>","link":"https:\/\/www.hindutamil.in\/news\/tamilnadu\/680124-nabard-bank-circular.html?frm=rss_more_article","image":["https:\/\/static.hindutamil.in\/hindu\/uploads\/news\/2021\/06\/09\/large\/680124.jpg"],"pubdate":"2021-06-09T03:31:13+00:00"},{"title":"சிறு குறு தொழில் பிரிவினரின் கடனுக்கு அவகாசம் வழங்க மத்திய அரசை வலியுறுத்துவோம்- 12 மாநில முதல்வர்களுக்கு தமிழக முதல்வர் ஸ்டாலின் கடிதம்","text":"<p><img src=\"https:\/\/static.hindutamil.in\/hindu\/uploads\/news\/2021\/06\/09\/large\/680121.jpg\" \/><\/p><p>குறு, சிறு நடுத்தர தொழில் நிறுவனத்தினர், சிறு கடனாளர்கள் 2 காலாண்டுக்கு கடனை திருப்பி செலுத்த கூடுதல் அவகாசம் வழங்குவது குறித்து மத்திய நிதியமைச்சர், ரிசர்வ் வங்கி ஆளுரை வலியறுத்த கோரி, 12 மாநில முதல்வர்களுக்கு முதல்வர் மு.க.ஸ்டாலின் கடிதம் எழுதியுள்ளார்.<\/p>\n\n<p>இதுதொடர்பாக ஆந்திரா, பிஹார், சத்தீஸ்கர், டெல்லி, ஜார்க்கண்ட், கேரளா, மகாராஷ்டிரா, ஒடிசா, பஞ்சாப், ராஜஸ்தான், தெலங்கானா, மேற்கு வங்கம் ஆகிய 12 மநில முதல்வர்களுக்கு முதல்வர் மு.க.ஸ்டாலின் கடிதம் எழுதியுள்ளார். கடிதத்தில் அவர் கூறியிருப்பதாவது:<\/p>","link":"https:\/\/www.hindutamil.in\/news\/tamilnadu\/680121-cm-stalin-letter-to-12-state-cm.html?frm=rss_more_article","image":["https:\/\/static.hindutamil.in\/hindu\/uploads\/news\/2021\/06\/09\/large\/680121.jpg"],"pubdate":"2021-06-09T03:31:11+00:00"},{"title":"சுற்றுச்சூழல் துறை அமைச்சர் வர தாமதம் பாதியில் வெளியேறிய சட்ட அமைச்சர்: புதுக்கோட்டை அரசு விழாவில் அலுவலர்கள் அதிர்ச்சி","text":"<p><img src=\"https:\/\/static.hindutamil.in\/hindu\/uploads\/news\/2021\/06\/09\/large\/680117.jpg\" \/><\/p><p>புதுக்கோட்டை அருகே நேற்று நடைபெற்ற அரசு விழாவுக்கு சுற்றுச்சூழல் துறை அமைச்சர் சிவ.வீ.மெய்யநாதன் வர தாமதம் ஏற்பட்டதால், அங்கு நீண்ட நேரம் காத்துஇருந்த சட்டத் துறை அமைச்சர் எஸ்.ரகுபதி திடீரென வெளியேறியது பரபரப்பை ஏற்படுத்தியுள்ளது.<\/p>\n\n<p>புதுக்கோட்டையில் மறைந்த சமூக ஆர்வலர் அருள்மொழியின் பிறந்தநாளை யொட்டி நேற்று ரூ.1.5 லட்சம் மதிப்பில் மருத்துவ உபகரணங்கள் வழங்கும் விழா நடைபெற்றது. இதில், சட்டத் துறை அமைச்சர் எஸ்.ரகுபதி, சுற்றுச்சூழல் துறை அமைச்சர் சிவ.வீ.மெய்யநாதன் ஆகியோர் கலந்துகொண்டனர்.<\/p>","link":"https:\/\/www.hindutamil.in\/news\/tamilnadu\/680117-law-minister-who-left-halfway-through-the-delay-of-environment-minister.html?frm=rss_more_article","image":["https:\/\/static.hindutamil.in\/hindu\/uploads\/news\/2021\/06\/09\/large\/680117.jpg"],"pubdate":"2021-06-09T03:31:09+00:00"},{"title":"தொடக்க வேளாண் கூட்டுறவு சங்கங்கள் மூலம் நடப்பு ஆண்டு ரூ.11,500 கோடி பயிர்க் கடன் வழங்க இலக்கு: கூட்டுறவுத் துறை அமைச்சர் ஐ.பெரியசாமி தகவல்","text":"<p><img src=\"https:\/\/static.hindutamil.in\/hindu\/uploads\/news\/2021\/06\/09\/large\/680118.jpg\" \/><\/p><p>தமிழகத்தில் தொடக்க வேளாண் கூட்டுறவு சங்கங்கள் மூலம் நடப்பு ஆண்டு விவசாயிகளுக்கு ரூ.11,500 கோடி பயிர்க் கடன் வழங்க இலக்குநிர்ணயிக்கப்பட்டுள்ளது என மாநிலகூட்டுறவுத் துறை அமைச்சர் ஐ.பெரியசாமி தெரிவித்தார்.<\/p>\n\n<p>தஞ்சாவூர் மாவட்ட ஆட்சியர் அலுவலகத்தில், தஞ்சாவூர், திருவாரூர், நாகை மாவட்டங்களில் குறுவை சாகுபடிக்கு கடன் வழங்குவது குறித்த ஆய்வுக் கூட்டம் நேற்று நடைபெற்றது. கூட்டத்துக்கு, அரசு தலைமைக் கொறடா கோவி.செழியன், ஆட்சியர் ம.கோவிந்தராவ் ஆகியோர் முன்னிலை வகித்தனர்.<\/p>","link":"https:\/\/www.hindutamil.in\/news\/tamilnadu\/680118-minister-i-periyasamy.html?frm=rss_more_article","image":["https:\/\/static.hindutamil.in\/hindu\/uploads\/news\/2021\/06\/09\/large\/680118.jpg"],"pubdate":"2021-06-09T03:31:09+00:00"}]