[{"title":"புதுக்கோட்டை நிதி நிறுவனத்தில் அலுவலர்களே திருடிய 305 பவுன் நகைகள்: போலீஸ் விசாரணை","text":"<p><img src=\"https:\/\/static.hindutamil.in\/hindu\/uploads\/news\/2021\/04\/23\/large\/662575.jpg\" \/><\/p><p>புதுக்கோட்டை தனியார் நிதி நிறுவனத்தில் 305 பவுன் நகைகளை அலுவலர்களே திருடியது குறித்து போலீஸார் வழக்குப் பதிவு செய்து விசாரித்து வருகின்றனர்.<\/p>\n\n<p>புதுக்கோட்டை தெற்கு 4-ம் வீதியில் தனியார் நிதி நிறுவனம் (எச்டிபி) உள்ளது. இங்கு, வாடிக்கையாளர்களுக்கு நகைக் கடன், தனிநபர் கடன், வாகனக் கடன் உள்ளிட்ட பலவிதமான கடன்கள் வழங்கப்படுகின்றன.<\/p>","link":"https:\/\/www.hindutamil.in\/news\/tamilnadu\/662575-305-pound-jewelery-stolen-by-officers-at-pudukkottai-financial-institution-police-investigation.html?frm=rss_more_article","image":["https:\/\/static.hindutamil.in\/hindu\/uploads\/news\/2021\/04\/23\/large\/662575.jpg"],"pubdate":"2021-04-23T12:29:42+00:00"},{"title":"ஹாட் லீக்ஸ்: அடிச்சுச் சொல்றோம்... அவங்க ஜெயிப்பாங்க!","text":"<p><img src=\"https:\/\/static.hindutamil.in\/hindu\/uploads\/news\/2021\/04\/23\/large\/662572.jpg\" \/><\/p><p>கோவை வடக்கு வடவள்ளி சண்முகசுந்தரம், மேட்டுப்பாளையம் டி.ஆர். சண்முகசுந்தரம், கவுண்டம்பாளையம் பையா கவுண்டர் - உதயசூரியன் வேட்பாளர்களாக களத்தில் நிற்கும் இந்த மூவருமே நிச்சயம் வெற்றி பெறுவார்கள் என உடன்பிறப்புகள் அடித்துச் சொல்கிறார்கள். மூவருமே ரியல் எஸ்டேட் தொழிலில் கொடி நாட்டியவர்கள் என்பதால் பணத்தை வாரி இறைத்திருக்கிறார்கள். வடவள்ளி சண்முக சுந்தரம் ரியல் எஸ்டேட் கம்பெனியில் தனக்கான பங்கைப் பிரித்து 10 கோடி ரூபாய்க்கு விற்று செலவழித்திருக்கிறாராம். இதையெல்லாம் வைத்து இந்த மூவரின் வெற்றி உறுதி என்கிறது திமுக வட்டாரம். ஆனால், மக்கள் என்ன முடிவெடுத்தார்களோ தெரியலையே சாமி!<\/p><p><a href=\"https:\/\/www.hindutamil.in\/news\/tamilnadu\/662572-hot-leaks.html?frm=rss_more_article\" style=\"color: #FF4422;\" target=\"_blank\">Source : www.hindutamil.in<\/a><\/p>","link":"https:\/\/www.hindutamil.in\/news\/tamilnadu\/662572-hot-leaks.html?frm=rss_more_article","image":["https:\/\/static.hindutamil.in\/hindu\/uploads\/news\/2021\/04\/23\/large\/662572.jpg"],"pubdate":"2021-04-23T12:10:36+00:00"},{"title":"முன்னாள் மத்திய அமைச்சர் ஈவிகேஎஸ் இளங்கோவனுக்கு கரோனா: மருத்துவமனையில் அனுமதி","text":"<p><img src=\"https:\/\/static.hindutamil.in\/hindu\/uploads\/news\/2021\/04\/23\/large\/662571.jpg\" \/><\/p><p>முன்னாள் மத்திய அமைச்சரும், தமிழக காங்கிரஸ் கமிட்டியின் முன்னாள் தலைவருமான ஈவிகேஎஸ் இளங்கோவனுக்கு கரோனா தொற்று உறுதியாகியுள்ளது. அவர் தனியார் மருத்துவமனையில் சிகிச்சைக்காக அனுமதிக்கப்பட்டுள்ளார்.<\/p>\n\n<p>தமிழகத்தில் கரோனா தொற்று வேகமாக அதிகரித்து வரும் நிலையில், அதன் தாக்கம் அனைவரையும் பாதித்து வருகிறது. தினசரி தொற்று எண்ணிக்கை 12 ஆயிரத்தைக் கடந்து செல்கிறது.<\/p>","link":"https:\/\/www.hindutamil.in\/news\/tamilnadu\/662571-corona-infection-former-union-minister-evks-ilangovan-hospitalization.html?frm=rss_more_article","image":["https:\/\/static.hindutamil.in\/hindu\/uploads\/news\/2021\/04\/23\/large\/662571.jpg"],"pubdate":"2021-04-23T12:07:26+00:00"},{"title":"ஹாட் லீக்ஸ்: அதிகாலையில் கொட்டிய கொலுசு மழை!","text":"<p><img src=\"https:\/\/static.hindutamil.in\/hindu\/uploads\/news\/2021\/04\/23\/large\/662570.jpg\" \/><\/p><p>கரூரில் முன்னாள் அமைச்சர் செந்தில் பாலாஜியும் இந்நாள் அமைச்சர் எம்.ஆர்.விஜய பாஸ்கரும் வாக்காளர்களை வளமாக<br \/>\nகவனித்து வைத்திருக்கிறார்களாம். &amp;ldquo;நீங்களும் குடுங்க... நாங்கள் குடுக்கிறோம். மக்கள்  யாருக்கு வேணும்னாலும் ஓட்டுப் போடட்டும். தேவையில்லாம புகாரெல்லாம் குடுத்து பிரச்சினையாக்க வேண்டாம்&amp;rdquo; என்பது இரண்டு தரப்பும் போட்டுக் கொண்ட ஒப்பந்தமாம்.<\/p>\n\n<p>இதன்படி, ஓட்டுக்கு 2 ஆயிரத்தை முதலில் இறக்கியது செந்தில் பாலாஜி தரப்பு. இதைப் பார்த்துவிட்டு ஓட்டுக்கு 3 ஆயிரம் என உயர்த்தியது விஜயபாஸ்கர் தரப்பு. சளைக்காத செந்தில்பாலாஜி தரப்பு, வாக்குப் பதிவு நாளன்று அதிகாலை 4 மணிக்கு வீட்டுக் கதவுகளைத் தட்டி பெண் வாக்காளர்களுக்கு வெள்ளிக் கொலுசும், ஆண் வாக்காளர்களுக்கு அட்வான்ஸ் டோக்கனும் கொடுத்து கவனிப்புக் கணக்கை முடித்தது. இதை சற்றும் எதிர்பார்க்காத விஜயபாஸ்கர் தரப்பு, கடைசி நேரத்தில் அத்தனை ஜோடி கொலுசுகளை எப்படிக் கொண்டு வந்தார்கள் என இப்போது களவிசாரணை நடத்திக் கொண்டிருக்கிறதாம்.<\/p>","link":"https:\/\/www.hindutamil.in\/news\/tamilnadu\/662570-hot-leaks.html?frm=rss_more_article","image":["https:\/\/static.hindutamil.in\/hindu\/uploads\/news\/2021\/04\/23\/large\/662570.jpg"],"pubdate":"2021-04-23T12:07:17+00:00"},{"title":"ஹாட் லீக்ஸ்: தடம் மாறிய தளவாய் பணம்","text":"<p><img src=\"https:\/\/static.hindutamil.in\/hindu\/uploads\/news\/2021\/04\/23\/large\/662569.jpg\" \/><\/p><p>கன்னியாகுமரி சட்டப்பேரவை தொகுதியில் போட்டியிட்ட தளவாய் சுந்தரம் ஓட்டுக்கு 500 ரூபாய் வீதம், ஒன்றரை லட்சம் வாக்குகளுக்கு கரன்ஸி கட்டுகளை இறக்கினாராம். ஆனால், ஓட்டுக்குக் கொடுத்த பணம் பாதி வழியிலேயே நின்றுவிட்டதாம். வாக்குப் பதிவு முடிந்த பின்பே இந்த ரகசியத்தை(!) தெரிந்து கொண்ட தளவாய், கட்சி நிர்வாகிகள் கூட்டத்தைக் கூட்டி பணத்தை பாதிவழியில் சுட்டவர்களை பெயரைக் சொல்லி அழைத்து ஒரு பிடி பிடித்தாராம். இவரை எதிர்த்துப் போட்டியிட்ட சிட்டிங் எம்எல்ஏவான திமுக வேட்பாளர் ஆஸ்டின், தனது வீட்டை அடகுவைத்து பணம் திரட்டி ஓட்டுக்குக் கொடுத்தாராம். தேர்தலில் வென்றுதான் இத்தனையும் மீட்க வேண்டும் போலிருக்கிறது!<\/p><p><a href=\"https:\/\/www.hindutamil.in\/news\/tamilnadu\/662569-hot-leaks.html?frm=rss_more_article\" style=\"color: #FF4422;\" target=\"_blank\">Source : www.hindutamil.in<\/a><\/p>","link":"https:\/\/www.hindutamil.in\/news\/tamilnadu\/662569-hot-leaks.html?frm=rss_more_article","image":["https:\/\/static.hindutamil.in\/hindu\/uploads\/news\/2021\/04\/23\/large\/662569.jpg"],"pubdate":"2021-04-23T12:05:27+00:00"},{"title":"அடுத்த 10 நாட்களுக்குத் தேவை; 20 லட்சம் தடுப்பூசிகள் அனுப்ப வேண்டும்: பிரதமருக்கு முதல்வர் பழனிசாமி கடிதம்","text":"<p><img src=\"https:\/\/static.hindutamil.in\/hindu\/uploads\/news\/2021\/04\/23\/large\/662565.jpg\" \/><\/p><p>தமிழகத்தில் அதிகரிக்கும் கரோனா தொற்றைத் தடுக்க, தடுப்பூசி இயக்கம் தடையின்றி நடக்க, 20 லட்சம் தடுப்பூசிகளை உடனடியாக வழங்க வேண்டும் என முதல்வர் பழனிசாமி பிரதமர் மோடிக்குக் கடிதம் எழுதியுள்ளார்.<\/p>\n\n<p>தடுப்பூசி வழங்குவது தொடர்பாக பிரதமர் மோடிக்கு, முதல்வர் பழனிசாமி எழுதிய கடிதம்:<\/p>","link":"https:\/\/www.hindutamil.in\/news\/tamilnadu\/662565-20-lakh-vaccines-should-be-sent-immediately-chief-minister-s-letter-to-the-prime-minister.html?frm=rss_more_article","image":["https:\/\/static.hindutamil.in\/hindu\/uploads\/news\/2021\/04\/23\/large\/662565.jpg"],"pubdate":"2021-04-23T11:44:23+00:00"},{"title":"கரோனா பாதிப்பு: கோட்டூர்புரம் உளவுத்துறை தலைமைக் காவலர் உயிரிழப்பு","text":"<p><img src=\"https:\/\/static.hindutamil.in\/hindu\/uploads\/news\/2021\/04\/23\/large\/662561.jpg\" \/><\/p><p>கரோனா தொற்றால் பாதிக்கப்பட்டு சிகிச்சை பெற்று வந்த கோட்டூர்புரம் உளவுப்பிரிவு தலைமைக் காவலர் சிகிச்சை பலனின்றி உயிரிழந்தார்.<\/p>\n\n<p>தமிழகத்தில் கரோனா தொற்று வேகமாகப் பரவி வருகிறது. தினசரி தொற்று எண்ணிக்கையும் வேகமாக உயர்ந்து வருகிறது. தமிழகத்தில் நேற்றைய கரோனா பாதிப்பு 12,652 ஆக உள்ளது. சென்னையின் நேற்றைய தொற்று 3,719 ஆக உயர்ந்துள்ளது.<\/p>","link":"https:\/\/www.hindutamil.in\/news\/tamilnadu\/662561-corona-infection-kotturpuram-intelligence-sec-hc-killed.html?frm=rss_more_article","image":["https:\/\/static.hindutamil.in\/hindu\/uploads\/news\/2021\/04\/23\/large\/662561.jpg"],"pubdate":"2021-04-23T10:45:00+00:00"},{"title":"ஏப்ரல் 23 சென்னை நிலவரம்; கரோனா தொற்றிலிருந்து மீண்டவர்கள், சிகிச்சையில் இருப்பவர்கள்: மண்டல வாரியான பட்டியல்","text":"<p><img src=\"https:\/\/static.hindutamil.in\/hindu\/uploads\/news\/2021\/04\/23\/large\/662560.jpg\" \/><\/p><p>சென்னையில் கரோனா தொற்றிலிருந்து மீண்டவர்கள், இறந்தவர்கள் மற்றும் சிகிச்சையில் இருப்போர் குறித்த பட்டியலை சென்னை மாநகராட்சி நாள்தோறும் வெளியிட்டு வருகிறது.<\/p>\n\n<p><strong>அதன்படி இன்று (ஏப்ரல் 23) வெளியிடப்பட்ட பட்டியல் இதோ:<\/strong><\/p>","link":"https:\/\/www.hindutamil.in\/news\/tamilnadu\/662560-april-23.html?frm=rss_more_article","image":["https:\/\/static.hindutamil.in\/hindu\/uploads\/news\/2021\/04\/23\/large\/662560.jpg"],"pubdate":"2021-04-23T10:20:50+00:00"},{"title":"திருமண அழைப்பிதழுடன் திருக்குறள் உரை நூல்கள்: காரைக்குடி பள்ளித் தாளாளரின் குறள் நேசம்","text":"<p><img src=\"https:\/\/static.hindutamil.in\/hindu\/uploads\/news\/2021\/04\/23\/large\/662553.jpg\" \/><\/p><p>காரைக்குடி தனியார் பள்ளி சார்பில் திருமண அழைப்பிதழுடன் வழங்கப்பட்ட திருக்குறள் உரைநூல்கள்.காரைக்குடி தனியார் பள்ளித் தாளாளர் தனது மகனின் திருமண அழைப்பிதழுடன் திருக்குறள் உரை நூல்களையும் நண்பர்கள், உறவினர்களுக்கு வழங்கி ஆச்சரியப்படுத்தி வருகிறார். <\/p>\n\n<p>வசதி படைத்தோரின் திருமண அழைப்பிதழ்கள் பெரும்பாலும் விலை உயர்ந்ததாகவும், பல்வேறு வடிவங்களிலும் இருக்கும். அந்த அழைப்பிதழ்கள் திருமணம் முடிந்தவுடன் பயனற்று போய் விடும்.  ஆனால், அதை மாற்றிக் காட்டும் விதமாக, காரைக்குடி செட்டிநாடு பப்ளிக் பள்ளித் தாளாளர் சுப.குமரேசன், தனது மகனின் திருமணத்துக்கு  வித்தியாசமான முறையில் திருமண அழைப்பிதழுடன் திருக்குறளுக்கான உரை நூல்களையும் வழங்கி வருகிறார்.<\/p>","link":"https:\/\/www.hindutamil.in\/news\/tamilnadu\/662553-tirukural-text-with-wedding-invitation.html?frm=rss_more_article","image":["https:\/\/static.hindutamil.in\/hindu\/uploads\/news\/2021\/04\/23\/large\/662553.jpg"],"pubdate":"2021-04-23T09:33:09+00:00"},{"title":"புலம்பெயர் தொழிலாளர்கள் நலனுக்கான அரசு அதிகாரிகள் குழுவில் மாற்றம்: தலைமை செயலர் ராஜீவ் ரஞ்சன் உத்தரவு","text":"<p><img src=\"https:\/\/static.hindutamil.in\/hindu\/uploads\/news\/2021\/04\/23\/large\/662542.jpg\" \/><\/p><p>கரோனா பரவலைக் கட்டுப்படுத்தும்நடவடிக்கையின் ஒரு பகுதியாக,புலம்பெயர் தொழிலாளர்களுக்கு உதவி செய்யும் வகையில் ஏற்கெனவே அமைக்கப்பட்ட குழுக்கள் மாற்றியமைக்கப்பட்டுள்ளன.<\/p>\n\n<p>கடந்த ஆண்டு மார்ச் மாதத்தில்முழு ஊரடங்கு அமல்படுத்தப்பட்டபோது அனைத்து மாநிலங்களிலும் வேலைக்காகச் சென்று தங்கியிருந்த புலம்பெயர் தொழிலாளர்கள், தங்கள் மாநிலங்களுக்கு சரக்கு வாகனங்கள், சைக்கிள்கள் மற்றும் நடந்தும் செல்லும் நிலை ஏற்பட்டது.<\/p>","link":"https:\/\/www.hindutamil.in\/news\/tamilnadu\/662542-migrant-workers.html?frm=rss_more_article","image":["https:\/\/static.hindutamil.in\/hindu\/uploads\/news\/2021\/04\/23\/large\/662542.jpg"],"pubdate":"2021-04-23T03:30:44+00:00"},{"title":"மருத்துவமனைகளில் படுக்கைகள் இல்லாததால் சிசிச்சை பெற முடியாமல் நோயாளிகள் அவதி; தமிழகத்தில் படுதீவிரமாக பரவுகிறது கரோனா: தினசரி பாதிப்பு 12 ஆயிரத்தை கடந்தது- பணிச் சுமையால் மருத்துவர்கள், சுகாதார ஊழியர்கள் பரிதவிப்பு","text":"<p><img src=\"https:\/\/static.hindutamil.in\/hindu\/uploads\/news\/2021\/04\/23\/large\/662534.jpg\" \/><\/p><p>தமிழகத்தில் கரோனா தொற்று பரவல் படுதீவிரமாகி வருகிறது. தினசரி பாதிப்பு 12 ஆயிரத்தை கடந்துள்ளது. மருத்துவமனைகளில் படுக்கைகள் நிரம்பி வழிவதால்புதிதாக தொற்றால் பாதிக்கப்படுபவர்கள் சிகிச்சை பெற முடியாமல் அவதிப்பட்டு வருகின்றனர். நோயாளிகள் அதிகரிப்பால் மருத்துவர்களும் சுகாதார ஊழியர்களும் பணிச் சுமையால் பரிதவிக்கின்றனர்.<\/p>\n\n<p>தமிழகத்தில் கடந்த மார்ச் மாதம் தொடங்கிய கரோனா தொற்றின் 2-வது அலை அதிவேகமாகப் பரவி வருகிறது. தினசரி பாதிப்பு12 ஆயிரத்தை கடந்துள்ளது. உயிரிழப்பும் 60-ஐ நெருங்கியுள்ளது. தொற்றால் பாதிக்கப்படுவோர் எண்ணிக்கை தொடர்ந்து அதிகரித்து வருவதால் அரசு மற்றும் தனியார் மருத்துவமனைகளில் படுக்கைகள் நிரம்பி வருகின்றன.<\/p>","link":"https:\/\/www.hindutamil.in\/news\/tamilnadu\/662534-covid-19-in-tamil-nadu.html?frm=rss_more_article","image":["https:\/\/static.hindutamil.in\/hindu\/uploads\/news\/2021\/04\/23\/large\/662534.jpg"],"pubdate":"2021-04-23T03:30:42+00:00"},{"title":"லலிதா ஜுவல்லரியில் நகைகள் திருடுபோன விவகாரம்; முக்கிய குற்றவாளியை பிடிக்க போலீஸார் தீவிரம்: திருடனின் நண்பர் ராஜஸ்தானில் பிடிபட்டார்","text":"<p><img src=\"https:\/\/static.hindutamil.in\/hindu\/uploads\/news\/2021\/04\/23\/large\/662515.jpg\" \/><\/p><p>லலிதா ஜுவல்லரி நகைக் கடையில் 5.5 கிலோ தங்கநகை திருடுபோன விவகாரத்தில் திருடனின் நண்பர் ராஜஸ்தானில் பிடிபட்டுள்ளார். முக்கிய குற்றவாளியைப் பிடிப்பதில் தனிப்படை போலீஸார் தீவிரமாக ஈடுபட்டுள்ளனர்.<\/p>\n\n<p>சென்னை தியாகராய நகரில் உள்ள லலிதா ஜுவல்லரி நகைக் கடைக்கு நகைகள் செய்யும் நகைப் பட்டறை அபிபுல்லா சாலையில் உள்ளது. இங்குள்ள நகைகளை தணிக்கை செய்தபோது 5.5 கிலோ தங்க நகைகள் திருடு போனது கண்டுபிடிக்கப்பட்டது.<\/p>","link":"https:\/\/www.hindutamil.in\/news\/tamilnadu\/662515-lalitha-jewellery-case.html?frm=rss_more_article","image":["https:\/\/static.hindutamil.in\/hindu\/uploads\/news\/2021\/04\/23\/large\/662515.jpg"],"pubdate":"2021-04-23T03:30:40+00:00"},{"title":"ஒரு வாரத்துக்கான தடுப்பூசி கையிருப்பில் உள்ளது: சில இடங்களில் தட்டுப்பாட்டால் அவதி","text":"<p><img src=\"https:\/\/static.hindutamil.in\/hindu\/uploads\/news\/2021\/04\/23\/large\/662513.jpg\" \/><\/p><p>தமிழகத்தில் இன்னும் ஒரு வாரத்துக்கான கரோனா தடுப்பூசி இருப்பில் உள்ளது. சில இடங்களில் தட்டுப்பாடு நிலவுவதால் ஊசி போட்டுக்கொள்ள வருபவர்கள் திருப்பி அனுப்பப்படுவதாக புகார் எழுந்துள்ளது.<\/p>\n\n<p>தமிழகத்தில் அரசு, தனியார் மருத்துவமனைகள் உட்பட சுமார் 5 ஆயிரம் மையங்களில் 45 வயதுக்கு மேற்பட்டவர்களுக்கு தடுப்பூசி போடப்படுகிறது. சராசரியாக தினமும் 50 ஆயிரத்துக்கும் மேற்பட்டவர்களுக்கு தடுப்பூசி போடப்பட்டு வருகிறது.<\/p>","link":"https:\/\/www.hindutamil.in\/news\/tamilnadu\/662513-covid-19-vaccines.html?frm=rss_more_article","image":["https:\/\/static.hindutamil.in\/hindu\/uploads\/news\/2021\/04\/23\/large\/662513.jpg"],"pubdate":"2021-04-23T03:30:40+00:00"},{"title":"ஊழியர்களின் பி.எப் தொகையில் ரூ.25 கோடி மோசடி புகார்- பேராயர் உள்ளிட்ட 4 பேர் மீது வழக்குப் பதிவு","text":"<p><img src=\"https:\/\/static.hindutamil.in\/hindu\/uploads\/news\/2021\/04\/23\/large\/662501.jpg\" \/><\/p><p>ஊழியர்களின் வருங்கால வைப்பு நிதி தொகையில் ரூ.25 கோடி மோசடிசெய்ததாக பேராயர் உள்ளிட்ட 4 பேர் மீது போலீஸார் வழக்குப்பதிவு செய்துள்ளனர்.<\/p>\n\n<p>கோவை போத்தனூர் அருகேஉள்ள, வெள்ளலூர் கிறிஸ்தவ ஆலயத்தின் தலைவர் மற்றும் போதகராக (பொறுப்பு) உள்ளவர் கெர்சோம் ஜேக்கப் (62). இவர், கோவை மாநகர குற்றப்பிரிவு போலீஸில் கடந்த 20-ம் தேதி ஒரு புகார் மனு அளித்தார். அதில் கூறியிருப்பதாவது:<\/p>","link":"https:\/\/www.hindutamil.in\/news\/tamilnadu\/662501-pf-fraud-case.html?frm=rss_more_article","image":["https:\/\/static.hindutamil.in\/hindu\/uploads\/news\/2021\/04\/23\/large\/662501.jpg"],"pubdate":"2021-04-23T03:30:39+00:00"},{"title":"கொசு மருந்து வாங்கியதாக போலியாக பில் தயாரித்து மதுரை மாநகராட்சியில் ரூ.88.88 லட்சம் முறைகேடு: முன்னாள் நகர்நல அலுவலர் உட்பட 6 பேர் மீது வழக்கு","text":"<p><img src=\"https:\/\/static.hindutamil.in\/hindu\/uploads\/news\/2021\/04\/23\/large\/662505.jpg\" \/><\/p><p>மதுரை மாநகராட்சியில் கொசு மருந்து வாங்கியதாக போலியாக பில் தயாரித்து ரூ.88.88 லட்சம் முறைகேடு செய்ததாக முன்னாள் நகர் நல அலுவலர் உட்பட 6 பேர் மீது லஞ்ச ஒழிப்பு போலீஸார் வழக்குப்பதிவு செய்துள்ளனர்.<\/p>\n\n<p>மதுரை மாநகராட்சியின் நகர் நலப் பிரிவில் கொசு மருந்து வாங்கியது தொடர்பாக தகவல் உரிமை சட்டத்தின்கீழ் ஒருவர் தகவல் பெற்றிருந்தார். இதில் முறைகேடு நடந்துள்ளதாக புகார் எழுந்தது.<\/p>","link":"https:\/\/www.hindutamil.in\/news\/tamilnadu\/662505-madurai-corporation.html?frm=rss_more_article","image":["https:\/\/static.hindutamil.in\/hindu\/uploads\/news\/2021\/04\/23\/large\/662505.jpg"],"pubdate":"2021-04-23T03:30:39+00:00"},{"title":"ஸ்டெர்லைட் எதிர்ப்பு ஊர்வலம் தொடர்பாக ஆவணங்களோ, ஆதாரங்களோ இல்லை: ஒருநபர் ஆணையத்தில் ரஜினி தகவல்","text":"<p><img src=\"https:\/\/static.hindutamil.in\/hindu\/uploads\/news\/2021\/04\/23\/large\/662502.jpg\" \/><\/p><p>தூத்துக்குடியில் நடைபெற்ற ஸ்டெர்லைட் எதிர்ப்பு ஊர்வலம் தொடர்பாக ஆவணங்களோ, ஆதாரங்களோ தன்னிடம் இல்லை என நடிகர் ரஜினிகாந்த், ஒருநபர் ஆணையத்திடம் எழுத்துபூர்வமாக தெரிவித்துள்ளார்.<\/p>\n\n<p>தூத்துக்குடியில் கடந்த 2018-ம்ஆண்டு மே மாதம் 22-ம் தேதி நடைபெற்ற துப்பாக்கி சூடு, தடியடிமற்றும் தொடர்ந்து நடந்த சம்பவங்களில் 13 பேர் பலியானார்கள். இதுதொடர்பாக, விசாரணை நடத்துவதற்காக, உயர் நீதிமன்ற ஓய்வுபெற்ற நீதிபதி அருணா ஜெகதீசன் தலைமையில் ஒருநபர் விசாரணை ஆணையத்தை தமிழக அரசு அமைத்தது.<\/p>","link":"https:\/\/www.hindutamil.in\/news\/tamilnadu\/662502-rajinikanth.html?frm=rss_more_article","image":["https:\/\/static.hindutamil.in\/hindu\/uploads\/news\/2021\/04\/23\/large\/662502.jpg"],"pubdate":"2021-04-23T03:30:39+00:00"},{"title":"எண்ணெய் வியாபாரி கொலை வழக்கில் 5 பேருக்கு ஆயுள் சிறை தண்டனை: கும்பகோணம் விரைவு நீதிமன்றம் தீர்ப்பு","text":"<p><img src=\"https:\/\/static.hindutamil.in\/hindu\/uploads\/news\/2021\/04\/23\/large\/662504.jpg\" \/><\/p><p>கும்பகோணம் எண்ணெய் வியாபாரி கொலை வழக்கில் 5 பேருக்கு ஆயுள் சிறை தண்டனை விதித்து, கும்பகோணம் கூடுதல் மாவட்ட விரைவு நீதிமன்றம் நேற்று தீர்ப்பளித்தது.<\/p>\n\n<p>தஞ்சாவூர் மாவட்டம், கும்பகோணம் மேலக்காவேரி பகுதியைச் சேர்ந்தவர் து.ராமநாதன் (63).எண்ணெய் வியாபாரியான இவரது வீட்டுக்கு கடந்த 15.3.2020 அன்று இரவு பத்திரிகை கொடுப்பதுபோல வந்த 5 பேர், ராமநாதனை கத்தியால் குத்திக் கொன்றுவிட்டு, அவரது மனைவி விஜயாவை தாக்கி, வீட்டில் இருந்த நகை மற்றும் பணத்தைக் கொள்ளையடித்துச் சென்றனர்.<\/p>","link":"https:\/\/www.hindutamil.in\/news\/tamilnadu\/662504-kumbakonam-court.html?frm=rss_more_article","image":["https:\/\/static.hindutamil.in\/hindu\/uploads\/news\/2021\/04\/23\/large\/662504.jpg"],"pubdate":"2021-04-23T03:30:39+00:00"},{"title":"மண்ணையும் மக்களையும் காக்க மரம் நடுவோம்: உலக பூமி தினத்தில் சத்குரு வேண்டுகோள்","text":"<p><img src=\"https:\/\/static.hindutamil.in\/hindu\/uploads\/news\/2021\/04\/23\/large\/662500.jpg\" \/><\/p><p>ஈஷா அறக்கட்டளை நிறுவனர் சத்குரு, உலக பூமி தினமான நேற்று வெளியிட்ட அறிக்கை:<\/p>\n\n<p>இந்தியாவில் ஏறத்தாழ 16 கோடி ஹெக்டேர் விளைநிலங்கள் உள்ளன. தண்ணீர் பற்றாக்குறை மற்றும் மண் வள குறைபாட்டின் காரணமாக விவசாயிகள் பெரும் சிரமத்தை எதிர்கொள்கின்றனர்.<\/p>","link":"https:\/\/www.hindutamil.in\/news\/tamilnadu\/662500-world-earth-day.html?frm=rss_more_article","image":["https:\/\/static.hindutamil.in\/hindu\/uploads\/news\/2021\/04\/23\/large\/662500.jpg"],"pubdate":"2021-04-23T03:30:39+00:00"},{"title":"‘கரோனா இல்லா சான்றுடன் நீலகிரி வரும் சுற்றுலா பயணிகளை அனுமதிக்க வேண்டும்’","text":"<p><img src=\"https:\/\/static.hindutamil.in\/hindu\/uploads\/news\/2021\/04\/23\/large\/662485.jpg\" \/><\/p><p>&amp;lsquo;கரோனா இல்லா&amp;rsquo; சான்றுடன்வரும் சுற்றுலா பயணிகளை நீலகிரி மாவட்டத்துக்குள் அனுமதிக்க வேண்டுமென வலியுறுத்தப்பட்டுள்ளது.<\/p>\n\n<p>இதுகுறித்து மார்க்சிஸ்ட் கம்யூனிஸ்ட் கட்சியின் மாவட்ட செயலாளர் வி.ஏ.பாஸ்கரன் கூறும்போது, &amp;quot;நீலகிரி மாவட்டத்தில் சுற்றுலாவை நம்பி ஆயிரக்கணக்கான குடும்பங்கள் உள்ளன.<\/p>","link":"https:\/\/www.hindutamil.in\/news\/tamilnadu\/662485-tourist-visiting-the-nilgiris.html?frm=rss_more_article","image":["https:\/\/static.hindutamil.in\/hindu\/uploads\/news\/2021\/04\/23\/large\/662485.jpg"],"pubdate":"2021-04-23T03:30:37+00:00"},{"title":"பிளாஸ்டிக் கழிவில் இருந்து இன்ஜின் ஆயில் உற்பத்தி செய்யும் ‘பைரோலிஸ் பிளாண்ட்’ - ஊழியர்களின்றி முடக்கம்","text":"<p><img src=\"https:\/\/static.hindutamil.in\/hindu\/uploads\/news\/2021\/04\/23\/large\/662476.jpg\" \/><\/p><p>உடுமலை நகராட்சிக்குட்பட்ட பகுதியில் நாளொன்றுக்கு 12 டன்மக்கும் குப்பை, 8 டன் மக்காதகுப்பை சேகரமாகிறது.பொள்ளாச்சி சாலையிலுள்ள நகராட்சிக்கு சொந்தமான உரக்கிடங்குக்கு அவை கொண்டு செல்லப்பட்டு அழிக்கப்படுகின்றன.<\/p>\n\n<p>இந்நிலையில், பிளாஸ்டிக் கழிவுகளை அழிக்கவும், அதன்மூலமாக இன்ஜின் ஆயில் எனப்படும் &amp;lsquo;பைரோலிஸ்&amp;#39; ஆயில் தயாரிக்கும் திட்டமும் கடந்த 4 ஆண்டுகளுக்கு முன் தொடங்கப்பட்டது. இதற்காக நகராட்சி சார்பில் ரூ.6 லட்சம் செலவில் ராட்சத கொதி கலன் மற்றும் குழாய்கள் ஏற்படுத்தப்பட்டன.<\/p>","link":"https:\/\/www.hindutamil.in\/news\/tamilnadu\/662476-engine-oil.html?frm=rss_more_article","image":["https:\/\/static.hindutamil.in\/hindu\/uploads\/news\/2021\/04\/23\/large\/662476.jpg"],"pubdate":"2021-04-23T03:30:35+00:00"},{"title":"கரோனா பரவலைத் தடுக்க காவல்துறை சார்பில் தினமும் 200 இடங்களில் விழிப்புணர்வு முகாம்: விதிகளை மீறுவோர் மீது கடும் நடவடிக்கை என ஆணையர் எச்சரிக்கை","text":"<p><img src=\"https:\/\/static.hindutamil.in\/hindu\/uploads\/news\/2021\/04\/23\/large\/662431.jpg\" \/><\/p><p>கரோனா வைரஸ் பரவலைத் தடுக்க சென்னை காவல்துறை சார்பில் தினமும் 200 இடங்களில் விழிப்புணர்வு முகாம் நடத்தப்படுகிறது. கரோனா தடுப்பு விதிகளை மீறுவோர் மீது கடும் நடவடிக்கை எடுக்கப்படும் என்று காவல் ஆணையர் மகேஷ் குமார் அகர்வால் தெரிவித்துள்ளார்.<\/p>\n\n<p>கரோனா தடுப்புப் பணியில் முன்கள வீரர்களாகச் செயல்படும் காவல் துறையினர் தொடர் விழிப்புணர்விலும் ஈடுபட்டு வருகின்றனர். அதன்படி, சென்னை அமைந்தகரையில் சென்னை பெருநகர போக்குவரத்து காவல் சார்பில் நடைபெற்ற கரோனா விழிப்புணர்வு முகாமில் காவல் ஆணையர் மகேஷ் குமார் அகர்வால் கலந்து கொண்டார். தொடர்ந்து கரோனா விழிப்புணர்வு சைக்கிள் பேரணியைத் தொடங்கி வைத்து பேசியதாவது:<\/p>","link":"https:\/\/www.hindutamil.in\/news\/tamilnadu\/662431-corona-awareness-programme.html?frm=rss_more_article","image":["https:\/\/static.hindutamil.in\/hindu\/uploads\/news\/2021\/04\/23\/large\/662431.jpg"],"pubdate":"2021-04-23T03:30:30+00:00"},{"title":"கட்டுமானப் பணிகளில் ஈடுபட்டுள்ள வடமாநிலங்களை சேர்ந்த தொழிலாளர்களுக்காக பிரத்யேக கரோனா மருத்துவமனைகள்: ‘கிரெடாய்’ உறுப்பினர்கள் முயற்சியால் பணிகள் தீவிரம்","text":"<p><img src=\"https:\/\/static.hindutamil.in\/hindu\/uploads\/news\/2021\/04\/23\/large\/662429.jpg\" \/><\/p><p>கட்டுமானப் பணிகளில் ஈடுபட்டுள்ள வட மாநிலங்களைச் சேர்ந்த தொழிலாளர்களுக்காக பிரத்யேக கரோனா மருத்துவமனைகளை அமைக்கும் முயற்சியில் &amp;lsquo;கிரெடாய்&amp;rsquo; உறுப்பினர்கள் தீவிரமாக ஈடுபட்டுள்ளனர்.<\/p>\n\n<p>கரோனா 2-வது அலை நாடு முழுவதும் வேகமாகப் பரவி வருகிறது. இந்நிலையில் தமிழகத்தில் ஞாயிறுதோறும் முழு ஊரடங்கும் மற்ற நாட்களில் இரவு நேர ஊரடங்கும் அமல்படுத்தப்பட்டுள்ளது. நாடு முழுவதும் முழு ஊரடங்கு அமல்படுத்தப்பட்டால், கடந்த முறை போல அவதிப்பட நேரிடுமோ என்ற அச்சத்தில் கோவை, திருப்பூர், சென்னை உள்ளிட்ட பல்வேறு நகரங்களில் கட்டுமானப் பணி, ஓட்டல்கள் உள்ளிட்டவற்றில் வேலை பார்க்கும் வடமாநிலத் தொழிலாளர்கள் தங்கள் சொந்த ஊருக்கு ரயில்களில் கூட்டம் கூட்டமாகச் செல்லத் தொடங்கியுள்ளனர்.<\/p>","link":"https:\/\/www.hindutamil.in\/news\/tamilnadu\/662429-credai.html?frm=rss_more_article","image":["https:\/\/static.hindutamil.in\/hindu\/uploads\/news\/2021\/04\/23\/large\/662429.jpg"],"pubdate":"2021-04-23T03:30:30+00:00"},{"title":"தேர்தலில் பதிவான தபால் வாக்குகளை மே 1-ம் தேதி பிரிப்பதை கைவிட வேண்டும்: தலைமை தேர்தல் அதிகாரியிடம் அதிமுக கோரிக்கை","text":"<p><img src=\"https:\/\/static.hindutamil.in\/hindu\/uploads\/news\/2021\/04\/23\/large\/662424.jpg\" \/><\/p><p>வாக்கு எண்ணிக்கை நாளான மே 2-ம் தேதிக்கு முன்னதாக 1-ம் தேதி, தபால் வாக்குகளைப் பிரிக்கும் பணியை மேற்கொள்ளக் கூடாது என்று அதிமுக சார்பில் தலைமை தேர்தல் அதிகாரியிடம் கோரிக்கை விடுக்கப்பட்டுள்ளதாக அமைச்சர் டி.ஜெயக்குமார் தெரிவித்தார்.<\/p>\n\n<p>தமிழக சட்டப்பேரவை பொதுத்தேர்தலில் பதிவான வாக்குகள் மே-2-ம் தேதி 76 மையங்களில் எண்ணப்படுகின்றன. இந்நிலையில், நேற்று தமிழக தலைமை தேர்தல் அதிகாரி சத்யபிரத சாஹூவிடம் அதிமுக சார்பில், அமைச்சர் டி.ஜெயக்குமார் தலைமையில் நிர்வாகிகள் கோரிக்கை மனு ஒன்றை அளித்தனர்.<\/p>","link":"https:\/\/www.hindutamil.in\/news\/tamilnadu\/662424-postal-votes.html?frm=rss_more_article","image":["https:\/\/static.hindutamil.in\/hindu\/uploads\/news\/2021\/04\/23\/large\/662424.jpg"],"pubdate":"2021-04-23T03:30:30+00:00"},{"title":"பதிவுச் சான்றுக்கு மாறாக ஆம்னி பேருந்துகளில் மாற்றம் செய்து இயக்கினால் 6 மாத சிறை தண்டனை: போக்குவரத்து ஆணையர் எச்சரிக்கை","text":"<p><img src=\"https:\/\/static.hindutamil.in\/hindu\/uploads\/news\/2021\/04\/23\/large\/662423.jpg\" \/><\/p><p>விதிகளை மீறி ஆம்னி பேருந்துகளில் மாற்றம் செய்தால் 6 மாத சிறை தண்டனை விதிக்கப்படும் என தமிழக போக்குவரத்துத் துறை எச்சரிக்கை விடுத்துள்ளது.<\/p>\n\n<p>இது தொடர்பாக தமிழக போக்குவரத்து ஆணையர் தென்காசி எஸ்.ஜவஹர் நேற்று வெளியிட்ட அறிவிப்பில் கூறியிருப்பதாவது:<\/p>","link":"https:\/\/www.hindutamil.in\/news\/tamilnadu\/662423-omni-buses.html?frm=rss_more_article","image":["https:\/\/static.hindutamil.in\/hindu\/uploads\/news\/2021\/04\/23\/large\/662423.jpg"],"pubdate":"2021-04-23T03:30:30+00:00"},{"title":"குப்பையில் கிடைத்த 10 பவுன் நகையை போலீஸில் ஒப்படைத்த தொழிலாளி","text":"<p><img src=\"https:\/\/static.hindutamil.in\/hindu\/uploads\/news\/2021\/04\/23\/large\/662420.jpg\" \/><\/p><p>சென்னை ராயபுரம் ஆஞ்சநேயர் கோயில் தெருவைச் சேர்ந்தவர் மோகனசுந்தரம் (55). இவர் சென்னை மாநகராட்சி தூய்மைப்  பணியாளராக வேலை செய்து வருகிறார். நேற்று காலையில் கொருக்குப்பேட்டை ஏகப்பன் தெரு குப்பைத் தொட்டியில் இருந்த குப்பையை தரம் பிரித்துக்கொண்டு இருந்தார். அப்போது அங்கிருந்த பையில்  தங்க நகைகள் இருப்பது தெரியவந்தது. உடனே மோகனசுந்தரம் நகையை கொருக்குப் பேட்டை போலீஸில் ஒப்படைத்தார்.<\/p>\n\n<p>இந்நிலையில் கொருக்குப்பேட்டை பகுதியை சேர்ந்த தேவி என்பவர் 10 பவுன் நகை, வீட்டிலிருந்து காணாமல் போயிருப்பதாக கொருக்குப்பேட்டை காவல் நிலையத்தில் புகார் ஒன்றை கொடுத்தார். தேவிக்கு திருமணம் நடைபெற இருப்பதும், அதற்காக பெற்றோர் சேர்த்து வைத்திருந்த நகை தவறுதலாக குப்பைத் தொட்டிக்கு சென்றதும், கொருக்குப்பேட்டை காவல் நிலைய ஆய்வாளர் தவமணியின் விசாரணையில் தெரியவந்தது. அதைத் தொடர்ந்து தொட்டியில் கிடைத்த நகையை காவல் ஆய்வாளர் தவமணி, திருமணப் பெண் தேவியிடம் ஒப்படைத்தார். நகையை கண்டுபிடித்து கொடுத்த மோகனசுந்தரத்தை போலீஸாரும், பொதுமக்களும் பாராட்டினர்.<\/p>","link":"https:\/\/www.hindutamil.in\/news\/tamilnadu\/662420-gold-in-garbage.html?frm=rss_more_article","image":["https:\/\/static.hindutamil.in\/hindu\/uploads\/news\/2021\/04\/23\/large\/662420.jpg"],"pubdate":"2021-04-23T03:30:29+00:00"}]